Strava_API/Strava_API.py
Strava_API/Strava_Bot.py
Strava_API/__init__.py
Strava_Social_Media_API-1.0.1.dist-info/LICENSE.txt
Strava_Social_Media_API-1.0.1.dist-info/METADATA
Strava_Social_Media_API-1.0.1.dist-info/WHEEL
Strava_Social_Media_API-1.0.1.dist-info/top_level.txt
Strava_Social_Media_API-1.0.1.dist-info/RECORD
