Metadata-Version: 2.1
Name: Strava-Social-Media-API
Version: 1.0.1
Summary: API fro Strava that interacts with the social media
Author: Tom
License-File: LICENSE.txt
Requires-Dist: os
Requires-Dist: shutil
Requires-Dist: glob
Requires-Dist: sys
Requires-Dist: random
Requires-Dist: selenium
Requires-Dist: time
Requires-Dist: datetime
Requires-Dist: json
